tree_sitter_pact/__init__.py
tree_sitter_pact/__init__.pyi
tree_sitter_pact/_binding.abi3.so
tree_sitter_pact/binding.c
tree_sitter_pact/py.typed
tree_sitter_pact/queries/folds.scm
tree_sitter_pact/queries/highlights.scm
tree_sitter_pact/queries/indents.scm
tree_sitter_pact/queries/injections.scm
tree_sitter_pact/queries/locals.scm
tree_sitter_pact/queries/tags.scm
tree_sitter_pact/queries/test.scm
tree_sitter_pact/queries/textobjects.scm
tree_sitter_pact-0.0.10.dist-info/METADATA
tree_sitter_pact-0.0.10.dist-info/WHEEL
tree_sitter_pact-0.0.10.dist-info/top_level.txt
tree_sitter_pact-0.0.10.dist-info/RECORD
tree_sitter_pact-0.0.10.dist-info/licenses/LICENCE
