Metadata-Version: 2.4
Name: tree-sitter-pact
Version: 0.0.10
Summary: Pact grammar for tree-sitter
Author-email: Salama Ashoush <salamaashoush@gmail.com>
License: MIT
Project-URL: Homepage, https://github.com/tree-sitter/tree-sitter-pact
Keywords: incremental,parsing,tree-sitter,pact
Classifier: Intended Audience :: Developers
Classifier: License :: OSI Approved :: MIT License
Classifier: Topic :: Software Development :: Compilers
Classifier: Topic :: Text Processing :: Linguistic
Classifier: Typing :: Typed
Requires-Python: >=3.10
License-File: LICENCE
Provides-Extra: core
Requires-Dist: tree-sitter~=0.24; extra == "core"
Dynamic: license-file
